README.md
setup.py
bin/cobble
cobblelib/__init__.py
cobblelib/aggregators.py
cobblelib/cli.py
cobblelib/commands.py
cobblelib/core.py
cobblelib/extractor.py
cobblelib/parsers.py
cobblelib/query_language.py
cobblelib/utils.py
cobblequery.egg-info/PKG-INFO
cobblequery.egg-info/SOURCES.txt
cobblequery.egg-info/dependency_links.txt
cobblequery.egg-info/requires.txt
cobblequery.egg-info/top_level.txt