Metadata-Version: 2.1
Name: cobblequery
Version: 1.0.2
Summary: CLI tool for doing data joining
Home-page: https://github.com/jdotpy/cobble
Author: KJ
Author-email: jdotpy@users.noreply.github.com
License: UNKNOWN
Download-URL: https://github.com/jdotpy/cobble/tarball/master
Keywords: tools
Platform: UNKNOWN
Classifier: Programming Language :: Python :: 3
